shelve_sqlite_zstd/__init__.py
shelve_sqlite_zstd/serialer.py
shelve_sqlite_zstd/shelve.py
shelve_sqlite_zstd/sqlite.py
shelve_sqlite_zstd/utils.py
shelve_sqlite_zstd/zstd.py
shelve_sqlite_zstd-0.2.1.dist-info/METADATA
shelve_sqlite_zstd-0.2.1.dist-info/WHEEL
shelve_sqlite_zstd-0.2.1.dist-info/RECORD
