Metadata-Version: 2.4
Name: shelve-sqlite-zstd
Version: 0.2.1
Summary: A lightweight Python package providing shelve-like persistent storage with zstd compression, SQLite transactions, multithreading support, and flexible serialization options.
Requires-Python: >=3.10
Requires-Dist: pydantic>=2.11.4
Requires-Dist: zstandard>=0.23.0
